habachen/__init__.pyi
habachen/_version.py
habachen/__init__.py
habachen/py.typed
habachen/_habachen.cpython-310-darwin.so
habachen-0.6.0.dist-info/RECORD
habachen-0.6.0.dist-info/WHEEL
habachen-0.6.0.dist-info/top_level.txt
habachen-0.6.0.dist-info/METADATA
habachen-0.6.0.dist-info/licenses/LICENSE
